pywavesurfer/__init__.py
pywavesurfer/ws.py
pywavesurfer-0.0.9.dist-info/METADATA
pywavesurfer-0.0.9.dist-info/WHEEL
pywavesurfer-0.0.9.dist-info/top_level.txt
pywavesurfer-0.0.9.dist-info/RECORD
