Metadata-Version: 2.1
Name: pywavesurfer
Version: 0.0.9
Summary: Python package for reading WaveSurfer data files
Home-page: https://github.com/JaneliaSciComp/PyWaveSurfer
Download-URL: https://github.com/JaneliaSciComp/PyWaveSurfer/archive/v0.0.9.tar.gz
Author: Adam L. Taylor, Boaz Mohar
Author-email: taylora@janelia.hhmi.org, boazmohar@gmail.com
Classifier: Development Status :: 3 - Alpha
Classifier: Programming Language :: Python :: 3
Classifier: Programming Language :: Python :: 3.8
Classifier: Programming Language :: Python :: 3.9
Classifier: Programming Language :: Python :: 3.10
Requires-Dist: numpy (==1.24.1)
Requires-Dist: packaging (==23.0)
Requires-Dist: h5py (==3.8.0)
Provides-Extra: dev
Requires-Dist: bump2version (==1.0.1) ; extra == 'dev'
Requires-Dist: numpy (==1.24.1) ; extra == 'dev'
Requires-Dist: packaging (==23.0) ; extra == 'dev'
Requires-Dist: h5py (==3.8.0) ; extra == 'dev'
Requires-Dist: pytest-cov (==4.0.0) ; extra == 'dev'
Requires-Dist: pytest (==7.2.1) ; extra == 'dev'
Requires-Dist: coveralls (==3.3.1) ; extra == 'dev'
